mws/__init__.py
mws/mws.py
mws/offamazonpayments.py
mws/utils.py
mws/future_utils/__init__.py
mws/future_utils/collections.py
mws/future_utils/crypto.py
mws/future_utils/deprecation.py
mws/future_utils/params.py
mws/future_utils/parsers.py
mws/future_utils/timezone.py
mws/future_utils/xml.py
mws-0.8.15.dist-info/AUTHORS
mws-0.8.15.dist-info/LICENSE
mws-0.8.15.dist-info/METADATA
mws-0.8.15.dist-info/WHEEL
mws-0.8.15.dist-info/top_level.txt
mws-0.8.15.dist-info/RECORD
