Metadata-Version: 2.1
Name: mws
Version: 0.8.15
Summary: Python library for interacting with the Amazon MWS API
Home-page: http://github.com/python-amazon-mws/python-amazon-mws
Maintainer: python-amazon-mws
Maintainer-email: python-amazon-mws@googlegroups.com
License: Unlicense
Download-URL: http://github.com/python-amazon-mws/python-amazon-mws/archive/v0.8.15.tar.gz
Platform: OS Independent
Classifier: Development Status :: 2 - Pre-Alpha
Classifier: Environment :: Web Environment
Classifier: Intended Audience :: Developers
Classifier: License :: OSI Approved :: BSD License
Classifier: Operating System :: OS Independent
Classifier: Programming Language :: Python
Classifier: Topic :: Internet :: WWW/HTTP :: Dynamic Content
Classifier: Topic :: Software Development
Classifier: Topic :: Software Development :: Libraries :: Application Frameworks
Classifier: Programming Language :: Python :: 3
Classifier: Programming Language :: Python :: 3.6
Classifier: Programming Language :: Python :: 3.7
Classifier: Programming Language :: Python :: 3.8
Classifier: Programming Language :: Python :: 3.9
Requires-Dist: requests
